README.md
pyproject.toml
setup.cfg
setup.py
src/accio/Assert.py
src/accio/Consts.py
src/accio/Email.py
src/accio/Excel.py
src/accio/Hash.py
src/accio/Http.py
src/accio/Log.py
src/accio/Session.py
src/accio/Shell.py
src/accio/Strtools.py
src/accio/__init__.py
src/accio/analysis_dubbo.py
src/accio/analysis_har.py
src/accio/analysis_jmx.py
src/accio/analysis_openapi.py
src/accio/analysis_postmanjson.py
src/accio/analysis_swagger.py
src/accio/case_generate.py
src/accio/case_generate_copy.py
src/accio/case_parameter.py
src/accio/config_file_parser.py
src/accio/conn_influxdb.py
src/accio/locust_creat_templatefile.py
src/accio/locust_get_runlog.py
src/accio/locust_read_csv.py
src/accio/locust_read_parameterfile.py
src/accio/locust_run.py
src/accio/logger.py
src/accio/module_detection.py
src/accio/parse_tools.py
src/accio/return_code.py
src/accio/timed_tasks.py
src/accio_api.egg-info/PKG-INFO
src/accio_api.egg-info/SOURCES.txt
src/accio_api.egg-info/dependency_links.txt
src/accio_api.egg-info/requires.txt
src/accio_api.egg-info/top_level.txt