Metadata-Version: 2.1
Name: accio-api
Version: 0.0.4
Summary: accio
Home-page: https://pypi.org/project/accio-api/
Author: accio
Author-email: xx@example.com
License: UNKNOWN
Platform: UNKNOWN
Classifier: Programming Language :: Python :: 3
Classifier: License :: OSI Approved :: MIT License
Classifier: Operating System :: OS Independent
Requires-Python: >=3.6
